kolibri_oidc_client_plugin/__init__.py
kolibri_oidc_client_plugin/auth.py
kolibri_oidc_client_plugin/kolibri_plugin.py
kolibri_oidc_client_plugin/options.py
kolibri_oidc_client_plugin/root_urls.py
kolibri_oidc_client_plugin/settings.py
kolibri_oidc_client_plugin/build/kolibri_oidc_client_plugin.openid_login_item_stats.json
kolibri_oidc_client_plugin/build/openid_login_item_stats.json
kolibri_oidc_client_plugin/static/kolibri_oidc_client_plugin.openid_login_item/kolibri_oidc_client_plugin.openid_login_item-0.3.2.js
kolibri_oidc_client_plugin/static/kolibri_oidc_client_plugin.openid_login_item/kolibri_oidc_client_plugin.openid_login_item-0.3.2.js.map
kolibri_oidc_client_plugin/static/kolibri_oidc_client_plugin.openid_login_item/kolibri_oidc_client_plugin.openid_login_item0.3.2.css
kolibri_oidc_client_plugin/static/kolibri_oidc_client_plugin.openid_login_item/kolibri_oidc_client_plugin.openid_login_item0.3.2.rtl.css
kolibri_oidc_client_plugin-0.3.2.dist-info/AUTHORS.rst
kolibri_oidc_client_plugin-0.3.2.dist-info/LICENSE
kolibri_oidc_client_plugin-0.3.2.dist-info/METADATA
kolibri_oidc_client_plugin-0.3.2.dist-info/WHEEL
kolibri_oidc_client_plugin-0.3.2.dist-info/entry_points.txt
kolibri_oidc_client_plugin-0.3.2.dist-info/top_level.txt
kolibri_oidc_client_plugin-0.3.2.dist-info/RECORD
