Metadata-Version: 2.1
Name: kolibri-oidc-client-plugin
Version: 0.3.2
Summary: Kolibri plugin to authenticate using an OpenID Connect provider
Home-page: https://github.com/learningequality/kolibri-oidc-client-plugin
Author: Learning Equality
Author-email: info@learningequality.org
License: MIT
Keywords: kolibri
Platform: UNKNOWN
Classifier: Development Status :: 4 - Beta
Classifier: Framework :: Django
Classifier: Intended Audience :: Developers
Classifier: License :: OSI Approved :: MIT License
Classifier: Natural Language :: English
Classifier: Programming Language :: Python :: 2
Classifier: Programming Language :: Python :: 2.7
Classifier: Programming Language :: Python :: 3
Classifier: Programming Language :: Python :: 3.3
Classifier: Programming Language :: Python :: 3.4
Classifier: Programming Language :: Python :: 3.5
Classifier: Programming Language :: Python :: Implementation :: PyPy
Classifier: Topic :: Education :: Computer Aided Instruction (CAI)
Classifier: Topic :: System :: Systems Administration :: Authentication/Directory
License-File: LICENSE
License-File: AUTHORS.rst
Requires-Dist: kolibri (>=0.15)
Requires-Dist: mozilla-django-oidc (==1.2.4)
Provides-Extra: dev
Requires-Dist: setuptools ; extra == 'dev'
Requires-Dist: twine ; extra == 'dev'
Requires-Dist: wheel (>=0.34.1) ; extra == 'dev'
